[
  {"id":"master_summary_for_pgy", "title":"⭐ PGY 必背 20 條（先看這個）", "emoji":"📋", "tag":"精華"},
  {"id":"exam_questions", "title":"📝 國考考古題 13 題（附解析）", "emoji":"📝", "tag":"精華"},
  {"id":"glossary_plain_chinese", "title":"📖 法律白話辭典（門外漢版）", "emoji":"📖", "tag":"精華"},
  {"id":"sop_when_sued", "title":"🆘 被告 SOP（萬一發生時）", "emoji":"🆘", "tag":"精華"},
  {"id":"insurance_guide", "title":"💼 保險與救濟全攻略", "emoji":"💼", "tag":"精華"},
  {"id":"pgy_legal_roadmap", "title":"🗺️ PGY → 主治法律地圖", "emoji":"🗺️", "tag":"精華"},
  {"id":"media_response_guide", "title":"📺 媒體應對指南", "emoji":"📺", "tag":"精華"},
  {"id":"complaint_types_guide", "title":"📞 7 種申訴類型圖解", "emoji":"📞", "tag":"精華"},
  {"id":"specialty_emergency", "title":"🚨 各科地雷：急診", "emoji":"🚨", "tag":"分科"},
  {"id":"specialty_surgery", "title":"🔪 各科地雷：外科", "emoji":"🔪", "tag":"分科"},
  {"id":"specialty_obgyn", "title":"👶 各科地雷：婦產科", "emoji":"👶", "tag":"分科"},
  {"id":"specialty_pediatrics", "title":"🧒 各科地雷：兒科", "emoji":"🧒", "tag":"分科"},
  {"id":"specialty_anesthesia", "title":"💉 各科地雷：麻醉", "emoji":"💉", "tag":"分科"},
  {"id":"specialty_internal_medicine", "title":"💊 各科地雷：內科", "emoji":"💊", "tag":"分科"},
  {"id":"case01_ob_ectopic_hsinchu", "title":"#01 子宮外孕（新竹）", "emoji":"⚠️", "tag":"刑事有罪"},
  {"id":"case02_surgery_laparoscopic_hsinchu_mackay", "title":"#02 腹腔鏡栓塞（新竹馬偕）", "emoji":"💉", "tag":"2198 萬"},
  {"id":"case03_ed_appendicitis_unreported", "title":"#03 闌尾炎未通知(桃園)", "emoji":"🚨", "tag":"後繼義務"},
  {"id":"case04_ed_head_trauma_ntu", "title":"#04 頭部外傷(台大)", "emoji":"🧠", "tag":"舉證轉換"},
  {"id":"case05_ob_newborn_death_taichung", "title":"#05 真空吸引(大里仁愛)", "emoji":"👶", "tag":"1404 萬"},
  {"id":"case06_ob_newborn_cp_vet", "title":"#06 胎心音漏判(北榮)", "emoji":"📈", "tag":"1905 萬"},
  {"id":"case07_cosmetic_liposuction_employee_death", "title":"#07 抽脂員工死(微笑)", "emoji":"⚖️", "tag":"刑事入獄"},
  {"id":"case08_cosmetic_rhinoplasty_malignant_hyperthermia", "title":"#08 隆鼻惡性高熱(葳亞娜)", "emoji":"🔥", "tag":"558 萬"},
  {"id":"case09_anesthesia_vegetative_state_tpe", "title":"#09 麻醉植物人(北聯醫)", "emoji":"💉", "tag":"4000 萬"},
  {"id":"case10_surgery_postop_records_amputation", "title":"#10 術後記錄(黃慧夫案)", "emoji":"🩹", "tag":"再審無罪"},
  {"id":"case11_cardiology_ecmo_delay_acquittal", "title":"#11 葉克膜延遲(無罪)", "emoji":"❤️", "tag":"工作條件"},
  {"id":"case12_surgery_icu_decision_acquittal", "title":"#12 未送 ICU(無罪)", "emoji":"🛡️", "tag":"裁量保護"},
  {"id":"case13_cosmetic_liposuction_postop_discharge", "title":"#13 抽脂後放走(入獄)", "emoji":"🚪", "tag":"術後義務"},
  {"id":"law01_criminal_liability_276", "title":"法律 1：刑法 §276", "emoji":"📖", "tag":"法理"},
  {"id":"law02_civil_burden_of_proof", "title":"法律 2：民事舉證", "emoji":"📖", "tag":"法理"},
  {"id":"law03_medical_act_82_amendment", "title":"法律 3：§82 修法", "emoji":"📖", "tag":"法理"},
  {"id":"law04_new_dispute_law_2024", "title":"法律 4：2024 新法", "emoji":"📖", "tag":"法理"},
  {"id":"guide01_top10_risk_situations", "title":"防身 1：Top 10 雷區", "emoji":"🛡️", "tag":"防身"},
  {"id":"guide02_informed_consent", "title":"防身 2：知情同意", "emoji":"🛡️", "tag":"防身"},
  {"id":"guide03_medical_records_law", "title":"防身 3：病歷寫法", "emoji":"🛡️", "tag":"防身"},
  {"id":"guide04_emergency_high_risk", "title":"防身 4：急診紅線", "emoji":"🛡️", "tag":"防身"},
  {"id":"stats01_litigation_statistics", "title":"統計：訴訟數據", "emoji":"📊", "tag":"數據"},
  {"id":"master_index", "title":"大師地圖（議題索引）", "emoji":"🗺️", "tag":"大師"},
  {"id":"master_yang_xiuyi", "title":"楊秀儀：知情同意/病人自主", "emoji":"🎓", "tag":"大師"},
  {"id":"master_wang_huang_yu", "title":"王皇玉：刑事過失/§82", "emoji":"🎓", "tag":"大師"},
  {"id":"master_wu_jun_ying", "title":"吳俊穎：糾紛實證/鑑定", "emoji":"🎓", "tag":"大師"},
  {"id":"master_hou_ying_ling", "title":"侯英泠：民事/比較法", "emoji":"🎓", "tag":"大師"},
  {"id":"master_yang_kun_ren", "title":"楊坤仁：實務(doctor119)", "emoji":"👨‍⚖️", "tag":"大師"},
  {"id":"master_wang_zhi_jia", "title":"王志嘉：TSGH/醫預法", "emoji":"👨‍⚖️", "tag":"大師"},
  {"id":"master_huang_ching_pin", "title":"黃清濱：醫師+律師", "emoji":"👨‍⚖️", "tag":"大師"}
]
